pdepy/__init__.py
pdepy/laplace.py
pdepy/parabolic.py
pdepy/steady.py
pdepy/time.py
pdepy/utils.py
pdepy/wave.py
pdepy-1.0.4.dist-info/LICENSE
pdepy-1.0.4.dist-info/METADATA
pdepy-1.0.4.dist-info/WHEEL
pdepy-1.0.4.dist-info/top_level.txt
pdepy-1.0.4.dist-info/RECORD
