Metadata-Version: 2.1
Name: pdepy
Version: 1.0.4
Summary: A Finite-Difference PDE solver.
Home-page: https://github.com/olivertso/pdepy
Author: Oliver Hung Buo Tso
Author-email: olivertsor@gmail.com
License: UNKNOWN
Keywords: partial-differential-equations finite-difference-method
Platform: UNKNOWN
Classifier: Intended Audience :: Developers
Classifier: Intended Audience :: Education
Classifier: Intended Audience :: Science/Research
Classifier: License :: OSI Approved :: MIT License
Classifier: Programming Language :: Python :: 3 :: Only
Classifier: Programming Language :: Python :: 3.6
Classifier: Programming Language :: Python :: 3.7
Classifier: Programming Language :: Python :: 3.8
Classifier: Programming Language :: Python :: Implementation :: CPython
Classifier: Topic :: Scientific/Engineering
Classifier: Topic :: Scientific/Engineering :: Mathematics
Classifier: Topic :: Scientific/Engineering :: Physics
Requires-Python: >=3.6
Requires-Dist: numpy (>=1.14.2)
Requires-Dist: scipy (>=1.0.0)
